stown/__main__.py
stown/core.py
stown/log.py
stown-1.1.0.dist-info/LICENSE
stown-1.1.0.dist-info/METADATA
stown-1.1.0.dist-info/WHEEL
stown-1.1.0.dist-info/entry_points.txt
stown-1.1.0.dist-info/top_level.txt
stown-1.1.0.dist-info/RECORD
