Metadata-Version: 2.2
Name: stown
Version: 1.1.0
Summary: Manage file system object mapping via symlinks. Lightweight alternative to GNU Stow.
Author: Ralph Seichter
Author-email: stown@seichter.de
Project-URL: Homepage, https://www.seichter.de/stown/
Project-URL: Issues, https://github.com/rseichter/stown/issues
Project-URL: Source, https://github.com/rseichter/stown
Keywords: symlinks-manager,symlinks,lightweight,dotfiles
Classifier: Development Status :: 5 - Production/Stable
Classifier: Operating System :: OS Independent
Classifier: Programming Language :: Python :: 3.9
Classifier: Topic :: Utilities
Requires-Python: >=3.9
License-File: LICENSE
